ervdetective/__init__.py
ervdetective/annotion_ervs.py
ervdetective/get_ervs.py
ervdetective/get_flank.py
ervdetective/main.py
ervdetective/map_genome.py
ervdetective/public_function.py
ervdetective/seqs_for_hmmer.py
ervdetective/simplify_gff3.py
ervdetective/simplify_hmmer.py
ervdetective/Internal_database/ERVprofiles/ERVprofile.zip
ervdetective/Internal_database/probe/ENV_probe.fasta
ervdetective/Internal_database/probe/GAG_probe.fasta
ervdetective/Internal_database/probe/RT_probe.fasta
ervdetective-1.0.9.dist-info/LICENSE
ervdetective-1.0.9.dist-info/METADATA
ervdetective-1.0.9.dist-info/WHEEL
ervdetective-1.0.9.dist-info/entry_points.txt
ervdetective-1.0.9.dist-info/top_level.txt
ervdetective-1.0.9.dist-info/RECORD
