Metadata-Version: 2.1
Name: ervdetective
Version: 1.0.9
Summary: An efficient pipeline for identification and annotation of endogenous retroviruses (ERVs)
Home-page: https://github.com/ZhijianZhou01/ervdetective
Author: Zhi-Jian Zhou
Author-email: zjzhou@hnu.edu.cn
Keywords: endogenous retroviruses,virus,evolution
Classifier: Development Status :: 5 - Production/Stable
Classifier: Environment :: Console
Classifier: Intended Audience :: Developers
Classifier: Intended Audience :: Science/Research
Classifier: Topic :: Scientific/Engineering
Classifier: Topic :: Scientific/Engineering :: Bio-Informatics
Classifier: Topic :: Scientific/Engineering :: Visualization
Classifier: Topic :: Scientific/Engineering :: Mathematics
Classifier: Programming Language :: Python :: 3.6
Classifier: Programming Language :: Python :: 3.7
Classifier: Programming Language :: Python :: 3.8
Classifier: Programming Language :: Python :: 3.9
Classifier: Programming Language :: Python :: 3.10
Classifier: Programming Language :: Python :: 3.11
Classifier: Programming Language :: Python :: 3.12
Classifier: Programming Language :: Python :: 3.13
Classifier: License :: OSI Approved :: GNU Lesser General Public License v2 or later (LGPLv2+)
Classifier: Operating System :: OS Independent
License-File: LICENSE
Requires-Dist: biopython >=1.77
